[
{
    "arguments": [
        "clang",
        "-I",
        "E:\\Qt_Install\\Tools\\QtCreator\\share\\qtcreator\\cplusplus\\wrappedMingwHeaders",
        "-I",
        "E:\\Qt_Install\\Tools\\QtCreator\\share\\qtcreator\\cplusplus\\wrappedQtHeaders",
        "-I",
        "E:\\Qt_Install\\Tools\\QtCreator\\share\\qtcreator\\cplusplus\\wrappedQtHeaders\\QtCore",
        "-I",
        "C:\\Users\\Mohammad\\AppData\\Local\\Temp\\QtCreator-FcfnYm\\clang-uiheader-ktjFwQ",
        "-nostdinc",
        "-nostdinc++",
        "-g",
        "-std=gnu++1z",
        "-Wall",
        "-Wextra",
        "-Wextra",
        "-fexceptions",
        "-mthreads",
        "-fsyntax-only",
        "-m64",
        "--target=x86_64-w64-mingw32",
        "-DQ_CREATOR_RUN",
        "-DUNICODE",
        "-D_UNICODE",
        "-DWIN32",
        "-DMINGW_HAS_SECURE_API",
        "-DQT_QML_DEBUG",
        "-DQT_NETWORK_LIB",
        "-DQT_CORE_LIB",
        "-I",
        "D:\\Daneshgah\\Term2\\AP\\AP_Project\\Main_Project\\jan-ghahve\\server",
        "-I",
        "E:\\Qt_Install\\6.2.4\\mingw_64\\include",
        "-I",
        "E:\\Qt_Install\\6.2.4\\mingw_64\\include\\QtNetwork",
        "-I",
        "E:\\Qt_Install\\6.2.4\\mingw_64\\include\\QtCore",
        "-I",
        "D:\\Daneshgah\\Term2\\AP\\AP_Project\\Main_Project\\jan-ghahve\\build-server-Desktop_Qt_6_2_4_MinGW_64_bit-Debug\\debug",
        "-I",
        "D:\\Daneshgah\\Term2\\AP\\AP_Project\\Main_Project\\jan-ghahve\\build-server-Desktop_Qt_6_2_4_MinGW_64_bit-Debug",
        "-I",
        "E:\\Qt_Install\\6.2.4\\mingw_64\\mkspecs\\win32-g++",
        "-isystem",
        "E:\\Qt_Install\\Tools\\mingw1120_64\\lib\\gcc\\x86_64-w64-mingw32\\11.2.0\\include\\c++",
        "-isystem",
        "E:\\Qt_Install\\Tools\\mingw1120_64\\lib\\gcc\\x86_64-w64-mingw32\\11.2.0\\include\\c++\\x86_64-w64-mingw32",
        "-isystem",
        "E:\\Qt_Install\\Tools\\mingw1120_64\\lib\\gcc\\x86_64-w64-mingw32\\11.2.0\\include\\c++\\backward",
        "-isystem",
        "E:\\Qt_Install\\Tools\\QtCreator\\bin\\clang\\lib\\clang\\14.0.3\\include",
        "-isystem",
        "E:\\Qt_Install\\Tools\\mingw1120_64\\x86_64-w64-mingw32\\include",
        "-fmessage-length=0",
        "-fdiagnostics-show-note-include-stack",
        "-fretain-comments-from-system-headers",
        "-fmacro-backtrace-limit=0",
        "-ferror-limit=1000",
        "-x",
        "c++",
        "-Wno-unknown-pragmas",
        "-Wno-unknown-warning-option",
        "-Wno-documentation-unknown-command",
        "-fno-delayed-template-parsing",
        "D:\\Daneshgah\\Term2\\AP\\AP_Project\\Main_Project\\jan-ghahve\\server\\Encryption\\myencryption.cpp"
    ],
    "directory": "D:/Daneshgah/Term2/AP/AP_Project/Main_Project/jan-ghahve/build-server-Desktop_Qt_6_2_4_MinGW_64_bit-Debug/.qtc_clangd",
    "file": "D:/Daneshgah/Term2/AP/AP_Project/Main_Project/jan-ghahve/server/Encryption/myencryption.cpp"
},
{
    "arguments": [
        "clang",
        "-I",
        "E:\\Qt_Install\\Tools\\QtCreator\\share\\qtcreator\\cplusplus\\wrappedMingwHeaders",
        "-I",
        "E:\\Qt_Install\\Tools\\QtCreator\\share\\qtcreator\\cplusplus\\wrappedQtHeaders",
        "-I",
        "E:\\Qt_Install\\Tools\\QtCreator\\share\\qtcreator\\cplusplus\\wrappedQtHeaders\\QtCore",
        "-I",
        "C:\\Users\\Mohammad\\AppData\\Local\\Temp\\QtCreator-FcfnYm\\clang-uiheader-ktjFwQ",
        "-nostdinc",
        "-nostdinc++",
        "-g",
        "-std=gnu++1z",
        "-Wall",
        "-Wextra",
        "-Wextra",
        "-fexceptions",
        "-mthreads",
        "-fsyntax-only",
        "-m64",
        "--target=x86_64-w64-mingw32",
        "-DQ_CREATOR_RUN",
        "-DUNICODE",
        "-D_UNICODE",
        "-DWIN32",
        "-DMINGW_HAS_SECURE_API",
        "-DQT_QML_DEBUG",
        "-DQT_NETWORK_LIB",
        "-DQT_CORE_LIB",
        "-I",
        "D:\\Daneshgah\\Term2\\AP\\AP_Project\\Main_Project\\jan-ghahve\\server",
        "-I",
        "E:\\Qt_Install\\6.2.4\\mingw_64\\include",
        "-I",
        "E:\\Qt_Install\\6.2.4\\mingw_64\\include\\QtNetwork",
        "-I",
        "E:\\Qt_Install\\6.2.4\\mingw_64\\include\\QtCore",
        "-I",
        "D:\\Daneshgah\\Term2\\AP\\AP_Project\\Main_Project\\jan-ghahve\\build-server-Desktop_Qt_6_2_4_MinGW_64_bit-Debug\\debug",
        "-I",
        "D:\\Daneshgah\\Term2\\AP\\AP_Project\\Main_Project\\jan-ghahve\\build-server-Desktop_Qt_6_2_4_MinGW_64_bit-Debug",
        "-I",
        "E:\\Qt_Install\\6.2.4\\mingw_64\\mkspecs\\win32-g++",
        "-isystem",
        "E:\\Qt_Install\\Tools\\mingw1120_64\\lib\\gcc\\x86_64-w64-mingw32\\11.2.0\\include\\c++",
        "-isystem",
        "E:\\Qt_Install\\Tools\\mingw1120_64\\lib\\gcc\\x86_64-w64-mingw32\\11.2.0\\include\\c++\\x86_64-w64-mingw32",
        "-isystem",
        "E:\\Qt_Install\\Tools\\mingw1120_64\\lib\\gcc\\x86_64-w64-mingw32\\11.2.0\\include\\c++\\backward",
        "-isystem",
        "E:\\Qt_Install\\Tools\\QtCreator\\bin\\clang\\lib\\clang\\14.0.3\\include",
        "-isystem",
        "E:\\Qt_Install\\Tools\\mingw1120_64\\x86_64-w64-mingw32\\include",
        "-fmessage-length=0",
        "-fdiagnostics-show-note-include-stack",
        "-fretain-comments-from-system-headers",
        "-fmacro-backtrace-limit=0",
        "-ferror-limit=1000",
        "-x",
        "c++",
        "-Wno-unknown-pragmas",
        "-Wno-unknown-warning-option",
        "-Wno-documentation-unknown-command",
        "-fno-delayed-template-parsing",
        "D:\\Daneshgah\\Term2\\AP\\AP_Project\\Main_Project\\jan-ghahve\\server\\Encryption\\qaesencryption.cpp"
    ],
    "directory": "D:/Daneshgah/Term2/AP/AP_Project/Main_Project/jan-ghahve/build-server-Desktop_Qt_6_2_4_MinGW_64_bit-Debug/.qtc_clangd",
    "file": "D:/Daneshgah/Term2/AP/AP_Project/Main_Project/jan-ghahve/server/Encryption/qaesencryption.cpp"
},
{
    "arguments": [
        "clang",
        "-I",
        "E:\\Qt_Install\\Tools\\QtCreator\\share\\qtcreator\\cplusplus\\wrappedMingwHeaders",
        "-I",
        "E:\\Qt_Install\\Tools\\QtCreator\\share\\qtcreator\\cplusplus\\wrappedQtHeaders",
        "-I",
        "E:\\Qt_Install\\Tools\\QtCreator\\share\\qtcreator\\cplusplus\\wrappedQtHeaders\\QtCore",
        "-I",
        "C:\\Users\\Mohammad\\AppData\\Local\\Temp\\QtCreator-FcfnYm\\clang-uiheader-ktjFwQ",
        "-nostdinc",
        "-nostdinc++",
        "-g",
        "-std=gnu++1z",
        "-Wall",
        "-Wextra",
        "-Wextra",
        "-fexceptions",
        "-mthreads",
        "-fsyntax-only",
        "-m64",
        "--target=x86_64-w64-mingw32",
        "-DQ_CREATOR_RUN",
        "-DUNICODE",
        "-D_UNICODE",
        "-DWIN32",
        "-DMINGW_HAS_SECURE_API",
        "-DQT_QML_DEBUG",
        "-DQT_NETWORK_LIB",
        "-DQT_CORE_LIB",
        "-I",
        "D:\\Daneshgah\\Term2\\AP\\AP_Project\\Main_Project\\jan-ghahve\\server",
        "-I",
        "E:\\Qt_Install\\6.2.4\\mingw_64\\include",
        "-I",
        "E:\\Qt_Install\\6.2.4\\mingw_64\\include\\QtNetwork",
        "-I",
        "E:\\Qt_Install\\6.2.4\\mingw_64\\include\\QtCore",
        "-I",
        "D:\\Daneshgah\\Term2\\AP\\AP_Project\\Main_Project\\jan-ghahve\\build-server-Desktop_Qt_6_2_4_MinGW_64_bit-Debug\\debug",
        "-I",
        "D:\\Daneshgah\\Term2\\AP\\AP_Project\\Main_Project\\jan-ghahve\\build-server-Desktop_Qt_6_2_4_MinGW_64_bit-Debug",
        "-I",
        "E:\\Qt_Install\\6.2.4\\mingw_64\\mkspecs\\win32-g++",
        "-isystem",
        "E:\\Qt_Install\\Tools\\mingw1120_64\\lib\\gcc\\x86_64-w64-mingw32\\11.2.0\\include\\c++",
        "-isystem",
        "E:\\Qt_Install\\Tools\\mingw1120_64\\lib\\gcc\\x86_64-w64-mingw32\\11.2.0\\include\\c++\\x86_64-w64-mingw32",
        "-isystem",
        "E:\\Qt_Install\\Tools\\mingw1120_64\\lib\\gcc\\x86_64-w64-mingw32\\11.2.0\\include\\c++\\backward",
        "-isystem",
        "E:\\Qt_Install\\Tools\\QtCreator\\bin\\clang\\lib\\clang\\14.0.3\\include",
        "-isystem",
        "E:\\Qt_Install\\Tools\\mingw1120_64\\x86_64-w64-mingw32\\include",
        "-fmessage-length=0",
        "-fdiagnostics-show-note-include-stack",
        "-fretain-comments-from-system-headers",
        "-fmacro-backtrace-limit=0",
        "-ferror-limit=1000",
        "-x",
        "c++",
        "-Wno-unknown-pragmas",
        "-Wno-unknown-warning-option",
        "-Wno-documentation-unknown-command",
        "-fno-delayed-template-parsing",
        "D:\\Daneshgah\\Term2\\AP\\AP_Project\\Main_Project\\jan-ghahve\\server\\channel.cpp"
    ],
    "directory": "D:/Daneshgah/Term2/AP/AP_Project/Main_Project/jan-ghahve/build-server-Desktop_Qt_6_2_4_MinGW_64_bit-Debug/.qtc_clangd",
    "file": "D:/Daneshgah/Term2/AP/AP_Project/Main_Project/jan-ghahve/server/channel.cpp"
},
{
    "arguments": [
        "clang",
        "-I",
        "E:\\Qt_Install\\Tools\\QtCreator\\share\\qtcreator\\cplusplus\\wrappedMingwHeaders",
        "-I",
        "E:\\Qt_Install\\Tools\\QtCreator\\share\\qtcreator\\cplusplus\\wrappedQtHeaders",
        "-I",
        "E:\\Qt_Install\\Tools\\QtCreator\\share\\qtcreator\\cplusplus\\wrappedQtHeaders\\QtCore",
        "-I",
        "C:\\Users\\Mohammad\\AppData\\Local\\Temp\\QtCreator-FcfnYm\\clang-uiheader-ktjFwQ",
        "-nostdinc",
        "-nostdinc++",
        "-g",
        "-std=gnu++1z",
        "-Wall",
        "-Wextra",
        "-Wextra",
        "-fexceptions",
        "-mthreads",
        "-fsyntax-only",
        "-m64",
        "--target=x86_64-w64-mingw32",
        "-DQ_CREATOR_RUN",
        "-DUNICODE",
        "-D_UNICODE",
        "-DWIN32",
        "-DMINGW_HAS_SECURE_API",
        "-DQT_QML_DEBUG",
        "-DQT_NETWORK_LIB",
        "-DQT_CORE_LIB",
        "-I",
        "D:\\Daneshgah\\Term2\\AP\\AP_Project\\Main_Project\\jan-ghahve\\server",
        "-I",
        "E:\\Qt_Install\\6.2.4\\mingw_64\\include",
        "-I",
        "E:\\Qt_Install\\6.2.4\\mingw_64\\include\\QtNetwork",
        "-I",
        "E:\\Qt_Install\\6.2.4\\mingw_64\\include\\QtCore",
        "-I",
        "D:\\Daneshgah\\Term2\\AP\\AP_Project\\Main_Project\\jan-ghahve\\build-server-Desktop_Qt_6_2_4_MinGW_64_bit-Debug\\debug",
        "-I",
        "D:\\Daneshgah\\Term2\\AP\\AP_Project\\Main_Project\\jan-ghahve\\build-server-Desktop_Qt_6_2_4_MinGW_64_bit-Debug",
        "-I",
        "E:\\Qt_Install\\6.2.4\\mingw_64\\mkspecs\\win32-g++",
        "-isystem",
        "E:\\Qt_Install\\Tools\\mingw1120_64\\lib\\gcc\\x86_64-w64-mingw32\\11.2.0\\include\\c++",
        "-isystem",
        "E:\\Qt_Install\\Tools\\mingw1120_64\\lib\\gcc\\x86_64-w64-mingw32\\11.2.0\\include\\c++\\x86_64-w64-mingw32",
        "-isystem",
        "E:\\Qt_Install\\Tools\\mingw1120_64\\lib\\gcc\\x86_64-w64-mingw32\\11.2.0\\include\\c++\\backward",
        "-isystem",
        "E:\\Qt_Install\\Tools\\QtCreator\\bin\\clang\\lib\\clang\\14.0.3\\include",
        "-isystem",
        "E:\\Qt_Install\\Tools\\mingw1120_64\\x86_64-w64-mingw32\\include",
        "-fmessage-length=0",
        "-fdiagnostics-show-note-include-stack",
        "-fretain-comments-from-system-headers",
        "-fmacro-backtrace-limit=0",
        "-ferror-limit=1000",
        "-x",
        "c++",
        "-Wno-unknown-pragmas",
        "-Wno-unknown-warning-option",
        "-Wno-documentation-unknown-command",
        "-fno-delayed-template-parsing",
        "D:\\Daneshgah\\Term2\\AP\\AP_Project\\Main_Project\\jan-ghahve\\server\\main.cpp"
    ],
    "directory": "D:/Daneshgah/Term2/AP/AP_Project/Main_Project/jan-ghahve/build-server-Desktop_Qt_6_2_4_MinGW_64_bit-Debug/.qtc_clangd",
    "file": "D:/Daneshgah/Term2/AP/AP_Project/Main_Project/jan-ghahve/server/main.cpp"
},
{
    "arguments": [
        "clang",
        "-I",
        "E:\\Qt_Install\\Tools\\QtCreator\\share\\qtcreator\\cplusplus\\wrappedMingwHeaders",
        "-I",
        "E:\\Qt_Install\\Tools\\QtCreator\\share\\qtcreator\\cplusplus\\wrappedQtHeaders",
        "-I",
        "E:\\Qt_Install\\Tools\\QtCreator\\share\\qtcreator\\cplusplus\\wrappedQtHeaders\\QtCore",
        "-I",
        "C:\\Users\\Mohammad\\AppData\\Local\\Temp\\QtCreator-FcfnYm\\clang-uiheader-ktjFwQ",
        "-nostdinc",
        "-nostdinc++",
        "-g",
        "-std=gnu++1z",
        "-Wall",
        "-Wextra",
        "-Wextra",
        "-fexceptions",
        "-mthreads",
        "-fsyntax-only",
        "-m64",
        "--target=x86_64-w64-mingw32",
        "-DQ_CREATOR_RUN",
        "-DUNICODE",
        "-D_UNICODE",
        "-DWIN32",
        "-DMINGW_HAS_SECURE_API",
        "-DQT_QML_DEBUG",
        "-DQT_NETWORK_LIB",
        "-DQT_CORE_LIB",
        "-I",
        "D:\\Daneshgah\\Term2\\AP\\AP_Project\\Main_Project\\jan-ghahve\\server",
        "-I",
        "E:\\Qt_Install\\6.2.4\\mingw_64\\include",
        "-I",
        "E:\\Qt_Install\\6.2.4\\mingw_64\\include\\QtNetwork",
        "-I",
        "E:\\Qt_Install\\6.2.4\\mingw_64\\include\\QtCore",
        "-I",
        "D:\\Daneshgah\\Term2\\AP\\AP_Project\\Main_Project\\jan-ghahve\\build-server-Desktop_Qt_6_2_4_MinGW_64_bit-Debug\\debug",
        "-I",
        "D:\\Daneshgah\\Term2\\AP\\AP_Project\\Main_Project\\jan-ghahve\\build-server-Desktop_Qt_6_2_4_MinGW_64_bit-Debug",
        "-I",
        "E:\\Qt_Install\\6.2.4\\mingw_64\\mkspecs\\win32-g++",
        "-isystem",
        "E:\\Qt_Install\\Tools\\mingw1120_64\\lib\\gcc\\x86_64-w64-mingw32\\11.2.0\\include\\c++",
        "-isystem",
        "E:\\Qt_Install\\Tools\\mingw1120_64\\lib\\gcc\\x86_64-w64-mingw32\\11.2.0\\include\\c++\\x86_64-w64-mingw32",
        "-isystem",
        "E:\\Qt_Install\\Tools\\mingw1120_64\\lib\\gcc\\x86_64-w64-mingw32\\11.2.0\\include\\c++\\backward",
        "-isystem",
        "E:\\Qt_Install\\Tools\\QtCreator\\bin\\clang\\lib\\clang\\14.0.3\\include",
        "-isystem",
        "E:\\Qt_Install\\Tools\\mingw1120_64\\x86_64-w64-mingw32\\include",
        "-fmessage-length=0",
        "-fdiagnostics-show-note-include-stack",
        "-fretain-comments-from-system-headers",
        "-fmacro-backtrace-limit=0",
        "-ferror-limit=1000",
        "-x",
        "c++",
        "-Wno-unknown-pragmas",
        "-Wno-unknown-warning-option",
        "-Wno-documentation-unknown-command",
        "-fno-delayed-template-parsing",
        "D:\\Daneshgah\\Term2\\AP\\AP_Project\\Main_Project\\jan-ghahve\\server\\myserver.cpp"
    ],
    "directory": "D:/Daneshgah/Term2/AP/AP_Project/Main_Project/jan-ghahve/build-server-Desktop_Qt_6_2_4_MinGW_64_bit-Debug/.qtc_clangd",
    "file": "D:/Daneshgah/Term2/AP/AP_Project/Main_Project/jan-ghahve/server/myserver.cpp"
},
{
    "arguments": [
        "clang",
        "-I",
        "E:\\Qt_Install\\Tools\\QtCreator\\share\\qtcreator\\cplusplus\\wrappedMingwHeaders",
        "-I",
        "E:\\Qt_Install\\Tools\\QtCreator\\share\\qtcreator\\cplusplus\\wrappedQtHeaders",
        "-I",
        "E:\\Qt_Install\\Tools\\QtCreator\\share\\qtcreator\\cplusplus\\wrappedQtHeaders\\QtCore",
        "-I",
        "C:\\Users\\Mohammad\\AppData\\Local\\Temp\\QtCreator-FcfnYm\\clang-uiheader-ktjFwQ",
        "-nostdinc",
        "-nostdinc++",
        "-g",
        "-std=gnu++1z",
        "-Wall",
        "-Wextra",
        "-Wextra",
        "-fexceptions",
        "-mthreads",
        "-fsyntax-only",
        "-m64",
        "--target=x86_64-w64-mingw32",
        "-DQ_CREATOR_RUN",
        "-DUNICODE",
        "-D_UNICODE",
        "-DWIN32",
        "-DMINGW_HAS_SECURE_API",
        "-DQT_QML_DEBUG",
        "-DQT_NETWORK_LIB",
        "-DQT_CORE_LIB",
        "-I",
        "D:\\Daneshgah\\Term2\\AP\\AP_Project\\Main_Project\\jan-ghahve\\server",
        "-I",
        "E:\\Qt_Install\\6.2.4\\mingw_64\\include",
        "-I",
        "E:\\Qt_Install\\6.2.4\\mingw_64\\include\\QtNetwork",
        "-I",
        "E:\\Qt_Install\\6.2.4\\mingw_64\\include\\QtCore",
        "-I",
        "D:\\Daneshgah\\Term2\\AP\\AP_Project\\Main_Project\\jan-ghahve\\build-server-Desktop_Qt_6_2_4_MinGW_64_bit-Debug\\debug",
        "-I",
        "D:\\Daneshgah\\Term2\\AP\\AP_Project\\Main_Project\\jan-ghahve\\build-server-Desktop_Qt_6_2_4_MinGW_64_bit-Debug",
        "-I",
        "E:\\Qt_Install\\6.2.4\\mingw_64\\mkspecs\\win32-g++",
        "-isystem",
        "E:\\Qt_Install\\Tools\\mingw1120_64\\lib\\gcc\\x86_64-w64-mingw32\\11.2.0\\include\\c++",
        "-isystem",
        "E:\\Qt_Install\\Tools\\mingw1120_64\\lib\\gcc\\x86_64-w64-mingw32\\11.2.0\\include\\c++\\x86_64-w64-mingw32",
        "-isystem",
        "E:\\Qt_Install\\Tools\\mingw1120_64\\lib\\gcc\\x86_64-w64-mingw32\\11.2.0\\include\\c++\\backward",
        "-isystem",
        "E:\\Qt_Install\\Tools\\QtCreator\\bin\\clang\\lib\\clang\\14.0.3\\include",
        "-isystem",
        "E:\\Qt_Install\\Tools\\mingw1120_64\\x86_64-w64-mingw32\\include",
        "-fmessage-length=0",
        "-fdiagnostics-show-note-include-stack",
        "-fretain-comments-from-system-headers",
        "-fmacro-backtrace-limit=0",
        "-ferror-limit=1000",
        "-x",
        "c++",
        "-Wno-unknown-pragmas",
        "-Wno-unknown-warning-option",
        "-Wno-documentation-unknown-command",
        "-fno-delayed-template-parsing",
        "D:\\Daneshgah\\Term2\\AP\\AP_Project\\Main_Project\\jan-ghahve\\server\\mythread.cpp"
    ],
    "directory": "D:/Daneshgah/Term2/AP/AP_Project/Main_Project/jan-ghahve/build-server-Desktop_Qt_6_2_4_MinGW_64_bit-Debug/.qtc_clangd",
    "file": "D:/Daneshgah/Term2/AP/AP_Project/Main_Project/jan-ghahve/server/mythread.cpp"
},
{
    "arguments": [
        "clang",
        "-I",
        "E:\\Qt_Install\\Tools\\QtCreator\\share\\qtcreator\\cplusplus\\wrappedMingwHeaders",
        "-I",
        "E:\\Qt_Install\\Tools\\QtCreator\\share\\qtcreator\\cplusplus\\wrappedQtHeaders",
        "-I",
        "E:\\Qt_Install\\Tools\\QtCreator\\share\\qtcreator\\cplusplus\\wrappedQtHeaders\\QtCore",
        "-I",
        "C:\\Users\\Mohammad\\AppData\\Local\\Temp\\QtCreator-FcfnYm\\clang-uiheader-ktjFwQ",
        "-nostdinc",
        "-nostdinc++",
        "-g",
        "-std=gnu++1z",
        "-Wall",
        "-Wextra",
        "-Wextra",
        "-fexceptions",
        "-mthreads",
        "-fsyntax-only",
        "-m64",
        "--target=x86_64-w64-mingw32",
        "-DQ_CREATOR_RUN",
        "-DUNICODE",
        "-D_UNICODE",
        "-DWIN32",
        "-DMINGW_HAS_SECURE_API",
        "-DQT_QML_DEBUG",
        "-DQT_NETWORK_LIB",
        "-DQT_CORE_LIB",
        "-I",
        "D:\\Daneshgah\\Term2\\AP\\AP_Project\\Main_Project\\jan-ghahve\\server",
        "-I",
        "E:\\Qt_Install\\6.2.4\\mingw_64\\include",
        "-I",
        "E:\\Qt_Install\\6.2.4\\mingw_64\\include\\QtNetwork",
        "-I",
        "E:\\Qt_Install\\6.2.4\\mingw_64\\include\\QtCore",
        "-I",
        "D:\\Daneshgah\\Term2\\AP\\AP_Project\\Main_Project\\jan-ghahve\\build-server-Desktop_Qt_6_2_4_MinGW_64_bit-Debug\\debug",
        "-I",
        "D:\\Daneshgah\\Term2\\AP\\AP_Project\\Main_Project\\jan-ghahve\\build-server-Desktop_Qt_6_2_4_MinGW_64_bit-Debug",
        "-I",
        "E:\\Qt_Install\\6.2.4\\mingw_64\\mkspecs\\win32-g++",
        "-isystem",
        "E:\\Qt_Install\\Tools\\mingw1120_64\\lib\\gcc\\x86_64-w64-mingw32\\11.2.0\\include\\c++",
        "-isystem",
        "E:\\Qt_Install\\Tools\\mingw1120_64\\lib\\gcc\\x86_64-w64-mingw32\\11.2.0\\include\\c++\\x86_64-w64-mingw32",
        "-isystem",
        "E:\\Qt_Install\\Tools\\mingw1120_64\\lib\\gcc\\x86_64-w64-mingw32\\11.2.0\\include\\c++\\backward",
        "-isystem",
        "E:\\Qt_Install\\Tools\\QtCreator\\bin\\clang\\lib\\clang\\14.0.3\\include",
        "-isystem",
        "E:\\Qt_Install\\Tools\\mingw1120_64\\x86_64-w64-mingw32\\include",
        "-fmessage-length=0",
        "-fdiagnostics-show-note-include-stack",
        "-fretain-comments-from-system-headers",
        "-fmacro-backtrace-limit=0",
        "-ferror-limit=1000",
        "-x",
        "c++",
        "-Wno-unknown-pragmas",
        "-Wno-unknown-warning-option",
        "-Wno-documentation-unknown-command",
        "-fno-delayed-template-parsing",
        "D:\\Daneshgah\\Term2\\AP\\AP_Project\\Main_Project\\jan-ghahve\\server\\smtp.cpp"
    ],
    "directory": "D:/Daneshgah/Term2/AP/AP_Project/Main_Project/jan-ghahve/build-server-Desktop_Qt_6_2_4_MinGW_64_bit-Debug/.qtc_clangd",
    "file": "D:/Daneshgah/Term2/AP/AP_Project/Main_Project/jan-ghahve/server/smtp.cpp"
},
{
    "arguments": [
        "clang",
        "-I",
        "E:\\Qt_Install\\Tools\\QtCreator\\share\\qtcreator\\cplusplus\\wrappedMingwHeaders",
        "-I",
        "E:\\Qt_Install\\Tools\\QtCreator\\share\\qtcreator\\cplusplus\\wrappedQtHeaders",
        "-I",
        "E:\\Qt_Install\\Tools\\QtCreator\\share\\qtcreator\\cplusplus\\wrappedQtHeaders\\QtCore",
        "-I",
        "C:\\Users\\Mohammad\\AppData\\Local\\Temp\\QtCreator-FcfnYm\\clang-uiheader-ktjFwQ",
        "-nostdinc",
        "-nostdinc++",
        "-g",
        "-std=gnu++1z",
        "-Wall",
        "-Wextra",
        "-Wextra",
        "-fexceptions",
        "-mthreads",
        "-fsyntax-only",
        "-m64",
        "--target=x86_64-w64-mingw32",
        "-DQ_CREATOR_RUN",
        "-DUNICODE",
        "-D_UNICODE",
        "-DWIN32",
        "-DMINGW_HAS_SECURE_API",
        "-DQT_QML_DEBUG",
        "-DQT_NETWORK_LIB",
        "-DQT_CORE_LIB",
        "-I",
        "D:\\Daneshgah\\Term2\\AP\\AP_Project\\Main_Project\\jan-ghahve\\server",
        "-I",
        "E:\\Qt_Install\\6.2.4\\mingw_64\\include",
        "-I",
        "E:\\Qt_Install\\6.2.4\\mingw_64\\include\\QtNetwork",
        "-I",
        "E:\\Qt_Install\\6.2.4\\mingw_64\\include\\QtCore",
        "-I",
        "D:\\Daneshgah\\Term2\\AP\\AP_Project\\Main_Project\\jan-ghahve\\build-server-Desktop_Qt_6_2_4_MinGW_64_bit-Debug\\debug",
        "-I",
        "D:\\Daneshgah\\Term2\\AP\\AP_Project\\Main_Project\\jan-ghahve\\build-server-Desktop_Qt_6_2_4_MinGW_64_bit-Debug",
        "-I",
        "E:\\Qt_Install\\6.2.4\\mingw_64\\mkspecs\\win32-g++",
        "-isystem",
        "E:\\Qt_Install\\Tools\\mingw1120_64\\lib\\gcc\\x86_64-w64-mingw32\\11.2.0\\include\\c++",
        "-isystem",
        "E:\\Qt_Install\\Tools\\mingw1120_64\\lib\\gcc\\x86_64-w64-mingw32\\11.2.0\\include\\c++\\x86_64-w64-mingw32",
        "-isystem",
        "E:\\Qt_Install\\Tools\\mingw1120_64\\lib\\gcc\\x86_64-w64-mingw32\\11.2.0\\include\\c++\\backward",
        "-isystem",
        "E:\\Qt_Install\\Tools\\QtCreator\\bin\\clang\\lib\\clang\\14.0.3\\include",
        "-isystem",
        "E:\\Qt_Install\\Tools\\mingw1120_64\\x86_64-w64-mingw32\\include",
        "-fmessage-length=0",
        "-fdiagnostics-show-note-include-stack",
        "-fretain-comments-from-system-headers",
        "-fmacro-backtrace-limit=0",
        "-ferror-limit=1000",
        "-x",
        "c++-header",
        "-Wno-unknown-pragmas",
        "-Wno-unknown-warning-option",
        "-Wno-documentation-unknown-command",
        "-fno-delayed-template-parsing",
        "D:\\Daneshgah\\Term2\\AP\\AP_Project\\Main_Project\\jan-ghahve\\server\\Encryption\\aesni_enc_cbc.h"
    ],
    "directory": "D:/Daneshgah/Term2/AP/AP_Project/Main_Project/jan-ghahve/build-server-Desktop_Qt_6_2_4_MinGW_64_bit-Debug/.qtc_clangd",
    "file": "D:/Daneshgah/Term2/AP/AP_Project/Main_Project/jan-ghahve/server/Encryption/aesni_enc_cbc.h"
},
{
    "arguments": [
        "clang",
        "-I",
        "E:\\Qt_Install\\Tools\\QtCreator\\share\\qtcreator\\cplusplus\\wrappedMingwHeaders",
        "-I",
        "E:\\Qt_Install\\Tools\\QtCreator\\share\\qtcreator\\cplusplus\\wrappedQtHeaders",
        "-I",
        "E:\\Qt_Install\\Tools\\QtCreator\\share\\qtcreator\\cplusplus\\wrappedQtHeaders\\QtCore",
        "-I",
        "C:\\Users\\Mohammad\\AppData\\Local\\Temp\\QtCreator-FcfnYm\\clang-uiheader-ktjFwQ",
        "-nostdinc",
        "-nostdinc++",
        "-g",
        "-std=gnu++1z",
        "-Wall",
        "-Wextra",
        "-Wextra",
        "-fexceptions",
        "-mthreads",
        "-fsyntax-only",
        "-m64",
        "--target=x86_64-w64-mingw32",
        "-DQ_CREATOR_RUN",
        "-DUNICODE",
        "-D_UNICODE",
        "-DWIN32",
        "-DMINGW_HAS_SECURE_API",
        "-DQT_QML_DEBUG",
        "-DQT_NETWORK_LIB",
        "-DQT_CORE_LIB",
        "-I",
        "D:\\Daneshgah\\Term2\\AP\\AP_Project\\Main_Project\\jan-ghahve\\server",
        "-I",
        "E:\\Qt_Install\\6.2.4\\mingw_64\\include",
        "-I",
        "E:\\Qt_Install\\6.2.4\\mingw_64\\include\\QtNetwork",
        "-I",
        "E:\\Qt_Install\\6.2.4\\mingw_64\\include\\QtCore",
        "-I",
        "D:\\Daneshgah\\Term2\\AP\\AP_Project\\Main_Project\\jan-ghahve\\build-server-Desktop_Qt_6_2_4_MinGW_64_bit-Debug\\debug",
        "-I",
        "D:\\Daneshgah\\Term2\\AP\\AP_Project\\Main_Project\\jan-ghahve\\build-server-Desktop_Qt_6_2_4_MinGW_64_bit-Debug",
        "-I",
        "E:\\Qt_Install\\6.2.4\\mingw_64\\mkspecs\\win32-g++",
        "-isystem",
        "E:\\Qt_Install\\Tools\\mingw1120_64\\lib\\gcc\\x86_64-w64-mingw32\\11.2.0\\include\\c++",
        "-isystem",
        "E:\\Qt_Install\\Tools\\mingw1120_64\\lib\\gcc\\x86_64-w64-mingw32\\11.2.0\\include\\c++\\x86_64-w64-mingw32",
        "-isystem",
        "E:\\Qt_Install\\Tools\\mingw1120_64\\lib\\gcc\\x86_64-w64-mingw32\\11.2.0\\include\\c++\\backward",
        "-isystem",
        "E:\\Qt_Install\\Tools\\QtCreator\\bin\\clang\\lib\\clang\\14.0.3\\include",
        "-isystem",
        "E:\\Qt_Install\\Tools\\mingw1120_64\\x86_64-w64-mingw32\\include",
        "-fmessage-length=0",
        "-fdiagnostics-show-note-include-stack",
        "-fretain-comments-from-system-headers",
        "-fmacro-backtrace-limit=0",
        "-ferror-limit=1000",
        "-x",
        "c++-header",
        "-Wno-unknown-pragmas",
        "-Wno-unknown-warning-option",
        "-Wno-documentation-unknown-command",
        "-fno-delayed-template-parsing",
        "D:\\Daneshgah\\Term2\\AP\\AP_Project\\Main_Project\\jan-ghahve\\server\\Encryption\\aesni_enc_ecb.h"
    ],
    "directory": "D:/Daneshgah/Term2/AP/AP_Project/Main_Project/jan-ghahve/build-server-Desktop_Qt_6_2_4_MinGW_64_bit-Debug/.qtc_clangd",
    "file": "D:/Daneshgah/Term2/AP/AP_Project/Main_Project/jan-ghahve/server/Encryption/aesni_enc_ecb.h"
},
{
    "arguments": [
        "clang",
        "-I",
        "E:\\Qt_Install\\Tools\\QtCreator\\share\\qtcreator\\cplusplus\\wrappedMingwHeaders",
        "-I",
        "E:\\Qt_Install\\Tools\\QtCreator\\share\\qtcreator\\cplusplus\\wrappedQtHeaders",
        "-I",
        "E:\\Qt_Install\\Tools\\QtCreator\\share\\qtcreator\\cplusplus\\wrappedQtHeaders\\QtCore",
        "-I",
        "C:\\Users\\Mohammad\\AppData\\Local\\Temp\\QtCreator-FcfnYm\\clang-uiheader-ktjFwQ",
        "-nostdinc",
        "-nostdinc++",
        "-g",
        "-std=gnu++1z",
        "-Wall",
        "-Wextra",
        "-Wextra",
        "-fexceptions",
        "-mthreads",
        "-fsyntax-only",
        "-m64",
        "--target=x86_64-w64-mingw32",
        "-DQ_CREATOR_RUN",
        "-DUNICODE",
        "-D_UNICODE",
        "-DWIN32",
        "-DMINGW_HAS_SECURE_API",
        "-DQT_QML_DEBUG",
        "-DQT_NETWORK_LIB",
        "-DQT_CORE_LIB",
        "-I",
        "D:\\Daneshgah\\Term2\\AP\\AP_Project\\Main_Project\\jan-ghahve\\server",
        "-I",
        "E:\\Qt_Install\\6.2.4\\mingw_64\\include",
        "-I",
        "E:\\Qt_Install\\6.2.4\\mingw_64\\include\\QtNetwork",
        "-I",
        "E:\\Qt_Install\\6.2.4\\mingw_64\\include\\QtCore",
        "-I",
        "D:\\Daneshgah\\Term2\\AP\\AP_Project\\Main_Project\\jan-ghahve\\build-server-Desktop_Qt_6_2_4_MinGW_64_bit-Debug\\debug",
        "-I",
        "D:\\Daneshgah\\Term2\\AP\\AP_Project\\Main_Project\\jan-ghahve\\build-server-Desktop_Qt_6_2_4_MinGW_64_bit-Debug",
        "-I",
        "E:\\Qt_Install\\6.2.4\\mingw_64\\mkspecs\\win32-g++",
        "-isystem",
        "E:\\Qt_Install\\Tools\\mingw1120_64\\lib\\gcc\\x86_64-w64-mingw32\\11.2.0\\include\\c++",
        "-isystem",
        "E:\\Qt_Install\\Tools\\mingw1120_64\\lib\\gcc\\x86_64-w64-mingw32\\11.2.0\\include\\c++\\x86_64-w64-mingw32",
        "-isystem",
        "E:\\Qt_Install\\Tools\\mingw1120_64\\lib\\gcc\\x86_64-w64-mingw32\\11.2.0\\include\\c++\\backward",
        "-isystem",
        "E:\\Qt_Install\\Tools\\QtCreator\\bin\\clang\\lib\\clang\\14.0.3\\include",
        "-isystem",
        "E:\\Qt_Install\\Tools\\mingw1120_64\\x86_64-w64-mingw32\\include",
        "-fmessage-length=0",
        "-fdiagnostics-show-note-include-stack",
        "-fretain-comments-from-system-headers",
        "-fmacro-backtrace-limit=0",
        "-ferror-limit=1000",
        "-x",
        "c++-header",
        "-Wno-unknown-pragmas",
        "-Wno-unknown-warning-option",
        "-Wno-documentation-unknown-command",
        "-fno-delayed-template-parsing",
        "D:\\Daneshgah\\Term2\\AP\\AP_Project\\Main_Project\\jan-ghahve\\server\\Encryption\\aesni_key_exp.h"
    ],
    "directory": "D:/Daneshgah/Term2/AP/AP_Project/Main_Project/jan-ghahve/build-server-Desktop_Qt_6_2_4_MinGW_64_bit-Debug/.qtc_clangd",
    "file": "D:/Daneshgah/Term2/AP/AP_Project/Main_Project/jan-ghahve/server/Encryption/aesni_key_exp.h"
},
{
    "arguments": [
        "clang",
        "-I",
        "E:\\Qt_Install\\Tools\\QtCreator\\share\\qtcreator\\cplusplus\\wrappedMingwHeaders",
        "-I",
        "E:\\Qt_Install\\Tools\\QtCreator\\share\\qtcreator\\cplusplus\\wrappedQtHeaders",
        "-I",
        "E:\\Qt_Install\\Tools\\QtCreator\\share\\qtcreator\\cplusplus\\wrappedQtHeaders\\QtCore",
        "-I",
        "C:\\Users\\Mohammad\\AppData\\Local\\Temp\\QtCreator-FcfnYm\\clang-uiheader-ktjFwQ",
        "-nostdinc",
        "-nostdinc++",
        "-g",
        "-std=gnu++1z",
        "-Wall",
        "-Wextra",
        "-Wextra",
        "-fexceptions",
        "-mthreads",
        "-fsyntax-only",
        "-m64",
        "--target=x86_64-w64-mingw32",
        "-DQ_CREATOR_RUN",
        "-DUNICODE",
        "-D_UNICODE",
        "-DWIN32",
        "-DMINGW_HAS_SECURE_API",
        "-DQT_QML_DEBUG",
        "-DQT_NETWORK_LIB",
        "-DQT_CORE_LIB",
        "-I",
        "D:\\Daneshgah\\Term2\\AP\\AP_Project\\Main_Project\\jan-ghahve\\server",
        "-I",
        "E:\\Qt_Install\\6.2.4\\mingw_64\\include",
        "-I",
        "E:\\Qt_Install\\6.2.4\\mingw_64\\include\\QtNetwork",
        "-I",
        "E:\\Qt_Install\\6.2.4\\mingw_64\\include\\QtCore",
        "-I",
        "D:\\Daneshgah\\Term2\\AP\\AP_Project\\Main_Project\\jan-ghahve\\build-server-Desktop_Qt_6_2_4_MinGW_64_bit-Debug\\debug",
        "-I",
        "D:\\Daneshgah\\Term2\\AP\\AP_Project\\Main_Project\\jan-ghahve\\build-server-Desktop_Qt_6_2_4_MinGW_64_bit-Debug",
        "-I",
        "E:\\Qt_Install\\6.2.4\\mingw_64\\mkspecs\\win32-g++",
        "-isystem",
        "E:\\Qt_Install\\Tools\\mingw1120_64\\lib\\gcc\\x86_64-w64-mingw32\\11.2.0\\include\\c++",
        "-isystem",
        "E:\\Qt_Install\\Tools\\mingw1120_64\\lib\\gcc\\x86_64-w64-mingw32\\11.2.0\\include\\c++\\x86_64-w64-mingw32",
        "-isystem",
        "E:\\Qt_Install\\Tools\\mingw1120_64\\lib\\gcc\\x86_64-w64-mingw32\\11.2.0\\include\\c++\\backward",
        "-isystem",
        "E:\\Qt_Install\\Tools\\QtCreator\\bin\\clang\\lib\\clang\\14.0.3\\include",
        "-isystem",
        "E:\\Qt_Install\\Tools\\mingw1120_64\\x86_64-w64-mingw32\\include",
        "-fmessage-length=0",
        "-fdiagnostics-show-note-include-stack",
        "-fretain-comments-from-system-headers",
        "-fmacro-backtrace-limit=0",
        "-ferror-limit=1000",
        "-x",
        "c++-header",
        "-Wno-unknown-pragmas",
        "-Wno-unknown-warning-option",
        "-Wno-documentation-unknown-command",
        "-fno-delayed-template-parsing",
        "D:\\Daneshgah\\Term2\\AP\\AP_Project\\Main_Project\\jan-ghahve\\server\\Encryption\\myencryption.h"
    ],
    "directory": "D:/Daneshgah/Term2/AP/AP_Project/Main_Project/jan-ghahve/build-server-Desktop_Qt_6_2_4_MinGW_64_bit-Debug/.qtc_clangd",
    "file": "D:/Daneshgah/Term2/AP/AP_Project/Main_Project/jan-ghahve/server/Encryption/myencryption.h"
},
{
    "arguments": [
        "clang",
        "-I",
        "E:\\Qt_Install\\Tools\\QtCreator\\share\\qtcreator\\cplusplus\\wrappedMingwHeaders",
        "-I",
        "E:\\Qt_Install\\Tools\\QtCreator\\share\\qtcreator\\cplusplus\\wrappedQtHeaders",
        "-I",
        "E:\\Qt_Install\\Tools\\QtCreator\\share\\qtcreator\\cplusplus\\wrappedQtHeaders\\QtCore",
        "-I",
        "C:\\Users\\Mohammad\\AppData\\Local\\Temp\\QtCreator-FcfnYm\\clang-uiheader-ktjFwQ",
        "-nostdinc",
        "-nostdinc++",
        "-g",
        "-std=gnu++1z",
        "-Wall",
        "-Wextra",
        "-Wextra",
        "-fexceptions",
        "-mthreads",
        "-fsyntax-only",
        "-m64",
        "--target=x86_64-w64-mingw32",
        "-DQ_CREATOR_RUN",
        "-DUNICODE",
        "-D_UNICODE",
        "-DWIN32",
        "-DMINGW_HAS_SECURE_API",
        "-DQT_QML_DEBUG",
        "-DQT_NETWORK_LIB",
        "-DQT_CORE_LIB",
        "-I",
        "D:\\Daneshgah\\Term2\\AP\\AP_Project\\Main_Project\\jan-ghahve\\server",
        "-I",
        "E:\\Qt_Install\\6.2.4\\mingw_64\\include",
        "-I",
        "E:\\Qt_Install\\6.2.4\\mingw_64\\include\\QtNetwork",
        "-I",
        "E:\\Qt_Install\\6.2.4\\mingw_64\\include\\QtCore",
        "-I",
        "D:\\Daneshgah\\Term2\\AP\\AP_Project\\Main_Project\\jan-ghahve\\build-server-Desktop_Qt_6_2_4_MinGW_64_bit-Debug\\debug",
        "-I",
        "D:\\Daneshgah\\Term2\\AP\\AP_Project\\Main_Project\\jan-ghahve\\build-server-Desktop_Qt_6_2_4_MinGW_64_bit-Debug",
        "-I",
        "E:\\Qt_Install\\6.2.4\\mingw_64\\mkspecs\\win32-g++",
        "-isystem",
        "E:\\Qt_Install\\Tools\\mingw1120_64\\lib\\gcc\\x86_64-w64-mingw32\\11.2.0\\include\\c++",
        "-isystem",
        "E:\\Qt_Install\\Tools\\mingw1120_64\\lib\\gcc\\x86_64-w64-mingw32\\11.2.0\\include\\c++\\x86_64-w64-mingw32",
        "-isystem",
        "E:\\Qt_Install\\Tools\\mingw1120_64\\lib\\gcc\\x86_64-w64-mingw32\\11.2.0\\include\\c++\\backward",
        "-isystem",
        "E:\\Qt_Install\\Tools\\QtCreator\\bin\\clang\\lib\\clang\\14.0.3\\include",
        "-isystem",
        "E:\\Qt_Install\\Tools\\mingw1120_64\\x86_64-w64-mingw32\\include",
        "-fmessage-length=0",
        "-fdiagnostics-show-note-include-stack",
        "-fretain-comments-from-system-headers",
        "-fmacro-backtrace-limit=0",
        "-ferror-limit=1000",
        "-x",
        "c++-header",
        "-Wno-unknown-pragmas",
        "-Wno-unknown-warning-option",
        "-Wno-documentation-unknown-command",
        "-fno-delayed-template-parsing",
        "D:\\Daneshgah\\Term2\\AP\\AP_Project\\Main_Project\\jan-ghahve\\server\\Encryption\\qaesencryption.h"
    ],
    "directory": "D:/Daneshgah/Term2/AP/AP_Project/Main_Project/jan-ghahve/build-server-Desktop_Qt_6_2_4_MinGW_64_bit-Debug/.qtc_clangd",
    "file": "D:/Daneshgah/Term2/AP/AP_Project/Main_Project/jan-ghahve/server/Encryption/qaesencryption.h"
},
{
    "arguments": [
        "clang",
        "-I",
        "E:\\Qt_Install\\Tools\\QtCreator\\share\\qtcreator\\cplusplus\\wrappedMingwHeaders",
        "-I",
        "E:\\Qt_Install\\Tools\\QtCreator\\share\\qtcreator\\cplusplus\\wrappedQtHeaders",
        "-I",
        "E:\\Qt_Install\\Tools\\QtCreator\\share\\qtcreator\\cplusplus\\wrappedQtHeaders\\QtCore",
        "-I",
        "C:\\Users\\Mohammad\\AppData\\Local\\Temp\\QtCreator-FcfnYm\\clang-uiheader-ktjFwQ",
        "-nostdinc",
        "-nostdinc++",
        "-g",
        "-std=gnu++1z",
        "-Wall",
        "-Wextra",
        "-Wextra",
        "-fexceptions",
        "-mthreads",
        "-fsyntax-only",
        "-m64",
        "--target=x86_64-w64-mingw32",
        "-DQ_CREATOR_RUN",
        "-DUNICODE",
        "-D_UNICODE",
        "-DWIN32",
        "-DMINGW_HAS_SECURE_API",
        "-DQT_QML_DEBUG",
        "-DQT_NETWORK_LIB",
        "-DQT_CORE_LIB",
        "-I",
        "D:\\Daneshgah\\Term2\\AP\\AP_Project\\Main_Project\\jan-ghahve\\server",
        "-I",
        "E:\\Qt_Install\\6.2.4\\mingw_64\\include",
        "-I",
        "E:\\Qt_Install\\6.2.4\\mingw_64\\include\\QtNetwork",
        "-I",
        "E:\\Qt_Install\\6.2.4\\mingw_64\\include\\QtCore",
        "-I",
        "D:\\Daneshgah\\Term2\\AP\\AP_Project\\Main_Project\\jan-ghahve\\build-server-Desktop_Qt_6_2_4_MinGW_64_bit-Debug\\debug",
        "-I",
        "D:\\Daneshgah\\Term2\\AP\\AP_Project\\Main_Project\\jan-ghahve\\build-server-Desktop_Qt_6_2_4_MinGW_64_bit-Debug",
        "-I",
        "E:\\Qt_Install\\6.2.4\\mingw_64\\mkspecs\\win32-g++",
        "-isystem",
        "E:\\Qt_Install\\Tools\\mingw1120_64\\lib\\gcc\\x86_64-w64-mingw32\\11.2.0\\include\\c++",
        "-isystem",
        "E:\\Qt_Install\\Tools\\mingw1120_64\\lib\\gcc\\x86_64-w64-mingw32\\11.2.0\\include\\c++\\x86_64-w64-mingw32",
        "-isystem",
        "E:\\Qt_Install\\Tools\\mingw1120_64\\lib\\gcc\\x86_64-w64-mingw32\\11.2.0\\include\\c++\\backward",
        "-isystem",
        "E:\\Qt_Install\\Tools\\QtCreator\\bin\\clang\\lib\\clang\\14.0.3\\include",
        "-isystem",
        "E:\\Qt_Install\\Tools\\mingw1120_64\\x86_64-w64-mingw32\\include",
        "-fmessage-length=0",
        "-fdiagnostics-show-note-include-stack",
        "-fretain-comments-from-system-headers",
        "-fmacro-backtrace-limit=0",
        "-ferror-limit=1000",
        "-x",
        "c++-header",
        "-Wno-unknown-pragmas",
        "-Wno-unknown-warning-option",
        "-Wno-documentation-unknown-command",
        "-fno-delayed-template-parsing",
        "D:\\Daneshgah\\Term2\\AP\\AP_Project\\Main_Project\\jan-ghahve\\server\\channel.h"
    ],
    "directory": "D:/Daneshgah/Term2/AP/AP_Project/Main_Project/jan-ghahve/build-server-Desktop_Qt_6_2_4_MinGW_64_bit-Debug/.qtc_clangd",
    "file": "D:/Daneshgah/Term2/AP/AP_Project/Main_Project/jan-ghahve/server/channel.h"
},
{
    "arguments": [
        "clang",
        "-I",
        "E:\\Qt_Install\\Tools\\QtCreator\\share\\qtcreator\\cplusplus\\wrappedMingwHeaders",
        "-I",
        "E:\\Qt_Install\\Tools\\QtCreator\\share\\qtcreator\\cplusplus\\wrappedQtHeaders",
        "-I",
        "E:\\Qt_Install\\Tools\\QtCreator\\share\\qtcreator\\cplusplus\\wrappedQtHeaders\\QtCore",
        "-I",
        "C:\\Users\\Mohammad\\AppData\\Local\\Temp\\QtCreator-FcfnYm\\clang-uiheader-ktjFwQ",
        "-nostdinc",
        "-nostdinc++",
        "-g",
        "-std=gnu++1z",
        "-Wall",
        "-Wextra",
        "-Wextra",
        "-fexceptions",
        "-mthreads",
        "-fsyntax-only",
        "-m64",
        "--target=x86_64-w64-mingw32",
        "-DQ_CREATOR_RUN",
        "-DUNICODE",
        "-D_UNICODE",
        "-DWIN32",
        "-DMINGW_HAS_SECURE_API",
        "-DQT_QML_DEBUG",
        "-DQT_NETWORK_LIB",
        "-DQT_CORE_LIB",
        "-I",
        "D:\\Daneshgah\\Term2\\AP\\AP_Project\\Main_Project\\jan-ghahve\\server",
        "-I",
        "E:\\Qt_Install\\6.2.4\\mingw_64\\include",
        "-I",
        "E:\\Qt_Install\\6.2.4\\mingw_64\\include\\QtNetwork",
        "-I",
        "E:\\Qt_Install\\6.2.4\\mingw_64\\include\\QtCore",
        "-I",
        "D:\\Daneshgah\\Term2\\AP\\AP_Project\\Main_Project\\jan-ghahve\\build-server-Desktop_Qt_6_2_4_MinGW_64_bit-Debug\\debug",
        "-I",
        "D:\\Daneshgah\\Term2\\AP\\AP_Project\\Main_Project\\jan-ghahve\\build-server-Desktop_Qt_6_2_4_MinGW_64_bit-Debug",
        "-I",
        "E:\\Qt_Install\\6.2.4\\mingw_64\\mkspecs\\win32-g++",
        "-isystem",
        "E:\\Qt_Install\\Tools\\mingw1120_64\\lib\\gcc\\x86_64-w64-mingw32\\11.2.0\\include\\c++",
        "-isystem",
        "E:\\Qt_Install\\Tools\\mingw1120_64\\lib\\gcc\\x86_64-w64-mingw32\\11.2.0\\include\\c++\\x86_64-w64-mingw32",
        "-isystem",
        "E:\\Qt_Install\\Tools\\mingw1120_64\\lib\\gcc\\x86_64-w64-mingw32\\11.2.0\\include\\c++\\backward",
        "-isystem",
        "E:\\Qt_Install\\Tools\\QtCreator\\bin\\clang\\lib\\clang\\14.0.3\\include",
        "-isystem",
        "E:\\Qt_Install\\Tools\\mingw1120_64\\x86_64-w64-mingw32\\include",
        "-fmessage-length=0",
        "-fdiagnostics-show-note-include-stack",
        "-fretain-comments-from-system-headers",
        "-fmacro-backtrace-limit=0",
        "-ferror-limit=1000",
        "-x",
        "c++-header",
        "-Wno-unknown-pragmas",
        "-Wno-unknown-warning-option",
        "-Wno-documentation-unknown-command",
        "-fno-delayed-template-parsing",
        "D:\\Daneshgah\\Term2\\AP\\AP_Project\\Main_Project\\jan-ghahve\\server\\myserver.h"
    ],
    "directory": "D:/Daneshgah/Term2/AP/AP_Project/Main_Project/jan-ghahve/build-server-Desktop_Qt_6_2_4_MinGW_64_bit-Debug/.qtc_clangd",
    "file": "D:/Daneshgah/Term2/AP/AP_Project/Main_Project/jan-ghahve/server/myserver.h"
},
{
    "arguments": [
        "clang",
        "-I",
        "E:\\Qt_Install\\Tools\\QtCreator\\share\\qtcreator\\cplusplus\\wrappedMingwHeaders",
        "-I",
        "E:\\Qt_Install\\Tools\\QtCreator\\share\\qtcreator\\cplusplus\\wrappedQtHeaders",
        "-I",
        "E:\\Qt_Install\\Tools\\QtCreator\\share\\qtcreator\\cplusplus\\wrappedQtHeaders\\QtCore",
        "-I",
        "C:\\Users\\Mohammad\\AppData\\Local\\Temp\\QtCreator-FcfnYm\\clang-uiheader-ktjFwQ",
        "-nostdinc",
        "-nostdinc++",
        "-g",
        "-std=gnu++1z",
        "-Wall",
        "-Wextra",
        "-Wextra",
        "-fexceptions",
        "-mthreads",
        "-fsyntax-only",
        "-m64",
        "--target=x86_64-w64-mingw32",
        "-DQ_CREATOR_RUN",
        "-DUNICODE",
        "-D_UNICODE",
        "-DWIN32",
        "-DMINGW_HAS_SECURE_API",
        "-DQT_QML_DEBUG",
        "-DQT_NETWORK_LIB",
        "-DQT_CORE_LIB",
        "-I",
        "D:\\Daneshgah\\Term2\\AP\\AP_Project\\Main_Project\\jan-ghahve\\server",
        "-I",
        "E:\\Qt_Install\\6.2.4\\mingw_64\\include",
        "-I",
        "E:\\Qt_Install\\6.2.4\\mingw_64\\include\\QtNetwork",
        "-I",
        "E:\\Qt_Install\\6.2.4\\mingw_64\\include\\QtCore",
        "-I",
        "D:\\Daneshgah\\Term2\\AP\\AP_Project\\Main_Project\\jan-ghahve\\build-server-Desktop_Qt_6_2_4_MinGW_64_bit-Debug\\debug",
        "-I",
        "D:\\Daneshgah\\Term2\\AP\\AP_Project\\Main_Project\\jan-ghahve\\build-server-Desktop_Qt_6_2_4_MinGW_64_bit-Debug",
        "-I",
        "E:\\Qt_Install\\6.2.4\\mingw_64\\mkspecs\\win32-g++",
        "-isystem",
        "E:\\Qt_Install\\Tools\\mingw1120_64\\lib\\gcc\\x86_64-w64-mingw32\\11.2.0\\include\\c++",
        "-isystem",
        "E:\\Qt_Install\\Tools\\mingw1120_64\\lib\\gcc\\x86_64-w64-mingw32\\11.2.0\\include\\c++\\x86_64-w64-mingw32",
        "-isystem",
        "E:\\Qt_Install\\Tools\\mingw1120_64\\lib\\gcc\\x86_64-w64-mingw32\\11.2.0\\include\\c++\\backward",
        "-isystem",
        "E:\\Qt_Install\\Tools\\QtCreator\\bin\\clang\\lib\\clang\\14.0.3\\include",
        "-isystem",
        "E:\\Qt_Install\\Tools\\mingw1120_64\\x86_64-w64-mingw32\\include",
        "-fmessage-length=0",
        "-fdiagnostics-show-note-include-stack",
        "-fretain-comments-from-system-headers",
        "-fmacro-backtrace-limit=0",
        "-ferror-limit=1000",
        "-x",
        "c++-header",
        "-Wno-unknown-pragmas",
        "-Wno-unknown-warning-option",
        "-Wno-documentation-unknown-command",
        "-fno-delayed-template-parsing",
        "D:\\Daneshgah\\Term2\\AP\\AP_Project\\Main_Project\\jan-ghahve\\server\\mythread.h"
    ],
    "directory": "D:/Daneshgah/Term2/AP/AP_Project/Main_Project/jan-ghahve/build-server-Desktop_Qt_6_2_4_MinGW_64_bit-Debug/.qtc_clangd",
    "file": "D:/Daneshgah/Term2/AP/AP_Project/Main_Project/jan-ghahve/server/mythread.h"
},
{
    "arguments": [
        "clang",
        "-I",
        "E:\\Qt_Install\\Tools\\QtCreator\\share\\qtcreator\\cplusplus\\wrappedMingwHeaders",
        "-I",
        "E:\\Qt_Install\\Tools\\QtCreator\\share\\qtcreator\\cplusplus\\wrappedQtHeaders",
        "-I",
        "E:\\Qt_Install\\Tools\\QtCreator\\share\\qtcreator\\cplusplus\\wrappedQtHeaders\\QtCore",
        "-I",
        "C:\\Users\\Mohammad\\AppData\\Local\\Temp\\QtCreator-FcfnYm\\clang-uiheader-ktjFwQ",
        "-nostdinc",
        "-nostdinc++",
        "-g",
        "-std=gnu++1z",
        "-Wall",
        "-Wextra",
        "-Wextra",
        "-fexceptions",
        "-mthreads",
        "-fsyntax-only",
        "-m64",
        "--target=x86_64-w64-mingw32",
        "-DQ_CREATOR_RUN",
        "-DUNICODE",
        "-D_UNICODE",
        "-DWIN32",
        "-DMINGW_HAS_SECURE_API",
        "-DQT_QML_DEBUG",
        "-DQT_NETWORK_LIB",
        "-DQT_CORE_LIB",
        "-I",
        "D:\\Daneshgah\\Term2\\AP\\AP_Project\\Main_Project\\jan-ghahve\\server",
        "-I",
        "E:\\Qt_Install\\6.2.4\\mingw_64\\include",
        "-I",
        "E:\\Qt_Install\\6.2.4\\mingw_64\\include\\QtNetwork",
        "-I",
        "E:\\Qt_Install\\6.2.4\\mingw_64\\include\\QtCore",
        "-I",
        "D:\\Daneshgah\\Term2\\AP\\AP_Project\\Main_Project\\jan-ghahve\\build-server-Desktop_Qt_6_2_4_MinGW_64_bit-Debug\\debug",
        "-I",
        "D:\\Daneshgah\\Term2\\AP\\AP_Project\\Main_Project\\jan-ghahve\\build-server-Desktop_Qt_6_2_4_MinGW_64_bit-Debug",
        "-I",
        "E:\\Qt_Install\\6.2.4\\mingw_64\\mkspecs\\win32-g++",
        "-isystem",
        "E:\\Qt_Install\\Tools\\mingw1120_64\\lib\\gcc\\x86_64-w64-mingw32\\11.2.0\\include\\c++",
        "-isystem",
        "E:\\Qt_Install\\Tools\\mingw1120_64\\lib\\gcc\\x86_64-w64-mingw32\\11.2.0\\include\\c++\\x86_64-w64-mingw32",
        "-isystem",
        "E:\\Qt_Install\\Tools\\mingw1120_64\\lib\\gcc\\x86_64-w64-mingw32\\11.2.0\\include\\c++\\backward",
        "-isystem",
        "E:\\Qt_Install\\Tools\\QtCreator\\bin\\clang\\lib\\clang\\14.0.3\\include",
        "-isystem",
        "E:\\Qt_Install\\Tools\\mingw1120_64\\x86_64-w64-mingw32\\include",
        "-fmessage-length=0",
        "-fdiagnostics-show-note-include-stack",
        "-fretain-comments-from-system-headers",
        "-fmacro-backtrace-limit=0",
        "-ferror-limit=1000",
        "-x",
        "c++-header",
        "-Wno-unknown-pragmas",
        "-Wno-unknown-warning-option",
        "-Wno-documentation-unknown-command",
        "-fno-delayed-template-parsing",
        "D:\\Daneshgah\\Term2\\AP\\AP_Project\\Main_Project\\jan-ghahve\\server\\smtp.h"
    ],
    "directory": "D:/Daneshgah/Term2/AP/AP_Project/Main_Project/jan-ghahve/build-server-Desktop_Qt_6_2_4_MinGW_64_bit-Debug/.qtc_clangd",
    "file": "D:/Daneshgah/Term2/AP/AP_Project/Main_Project/jan-ghahve/server/smtp.h"
}
]